{
    "message": "The data were fetched successfully.",
    "data": {
        "records": [
            {
                "date": "2022-07-26",
                "day": 153,
                "resource": "https://www.facebook.com/MinistryofDefence.UA/posts/pfbid02wUDUVf7uYWD1J95zxNET95ufhETq2ihPa841CLANVszc1wNqgz9Fqeiax2VMyZMbl",
                "stats": {
                    "personnel_units": 39870,
                    "tanks": 1737,
                    "armoured_fighting_vehicles": 3959,
                    "artillery_systems": 880,
                    "mlrs": 258,
                    "aa_warfare_systems": 117,
                    "planes": 222,
                    "helicopters": 189,
                    "vehicles_fuel_tanks": 2835,
                    "warships_cutters": 15,
                    "cruise_missiles": 174,
                    "uav_systems": 722,
                    "special_military_equip": 75,
                    "atgm_srbm_systems": 4
                }
            },
            {
                "date": "2022-07-27",
                "day": 154,
                "resource": "https://www.facebook.com/MinistryofDefence.UA/posts/pfbid02CZkjLuNMZ6RDdYWQn8T6Nw8iYf9byd6KrBofWKQZroW59trdmWBmoiw4H496YWVCl",
                "stats": {
                    "personnel_units": 40070,
                    "tanks": 1738,
                    "armoured_fighting_vehicles": 3971,
                    "artillery_systems": 883,
                    "mlrs": 258,
                    "aa_warfare_systems": 117,
                    "planes": 222,
                    "helicopters": 190,
                    "vehicles_fuel_tanks": 2847,
                    "warships_cutters": 15,
                    "cruise_missiles": 174,
                    "uav_systems": 726,
                    "special_military_equip": 75,
                    "atgm_srbm_systems": 4
                }
            },
            {
                "date": "2022-07-28",
                "day": 155,
                "resource": "https://www.facebook.com/MinistryofDefence.UA/posts/pfbid02t6qfXZBJNUny47ofJJE8e1PJy4dAYXA5daECJucUaePrKMYZSDBJUazU4aChL5Zpl",
                "stats": {
                    "personnel_units": 40230,
                    "tanks": 1742,
                    "armoured_fighting_vehicles": 3979,
                    "artillery_systems": 894,
                    "mlrs": 258,
                    "aa_warfare_systems": 117,
                    "planes": 222,
                    "helicopters": 190,
                    "vehicles_fuel_tanks": 2854,
                    "warships_cutters": 15,
                    "cruise_missiles": 174,
                    "uav_systems": 729,
                    "special_military_equip": 75,
                    "atgm_srbm_systems": 4
                }
            },
            {
                "date": "2022-07-29",
                "day": 156,
                "resource": "https://www.facebook.com/MinistryofDefence.UA/posts/pfbid09JpisDViRZfikL8yCmGJCYgyZPKgTHmMHpazo81vPUK8PgRUYyBqprgx5YZ8wdpdl",
                "stats": {
                    "personnel_units": 40500,
                    "tanks": 1749,
                    "armoured_fighting_vehicles": 3987,
                    "artillery_systems": 900,
                    "mlrs": 258,
                    "aa_warfare_systems": 117,
                    "planes": 222,
                    "helicopters": 190,
                    "vehicles_fuel_tanks": 2870,
                    "warships_cutters": 15,
                    "cruise_missiles": 174,
                    "uav_systems": 731,
                    "special_military_equip": 77,
                    "atgm_srbm_systems": 4
                }
            },
            {
                "date": "2022-07-30",
                "day": 157,
                "resource": "https://www.facebook.com/MinistryofDefence.UA/posts/pfbid0ATDucSNgshUTuUZnY3uhJbfwUbBBq1RH1mvpogDyAfsyiaKenVaSwEorxVJkPC7Cl",
                "stats": {
                    "personnel_units": 40670,
                    "tanks": 1759,
                    "armoured_fighting_vehicles": 3995,
                    "artillery_systems": 906,
                    "mlrs": 258,
                    "aa_warfare_systems": 117,
                    "planes": 222,
                    "helicopters": 190,
                    "vehicles_fuel_tanks": 2889,
                    "warships_cutters": 15,
                    "cruise_missiles": 174,
                    "uav_systems": 733,
                    "special_military_equip": 78,
                    "atgm_srbm_systems": 4
                }
            },
            {
                "date": "2022-07-31",
                "day": 158,
                "resource": "https://www.facebook.com/MinistryofDefence.UA/posts/pfbid02d3AJGPVncW9U1i5782uhBYpMYnduykwPeNXG9rzFv9mvFm7qqXEqufp1WN2o2tczl",
                "stats": {
                    "personnel_units": 40830,
                    "tanks": 1763,
                    "armoured_fighting_vehicles": 4004,
                    "artillery_systems": 916,
                    "mlrs": 259,
                    "aa_warfare_systems": 117,
                    "planes": 223,
                    "helicopters": 190,
                    "vehicles_fuel_tanks": 2902,
                    "warships_cutters": 15,
                    "cruise_missiles": 174,
                    "uav_systems": 735,
                    "special_military_equip": 80,
                    "atgm_srbm_systems": 4
                }
            },
            {
                "date": "2022-08-01",
                "day": 159,
                "resource": "https://www.facebook.com/MinistryofDefence.UA/posts/pfbid0NmZvH2evhXh9QywbmdfvcRMhM6JP67ZKKaypj11eUhaZkqYfdMTBP4FH24knB8url",
                "stats": {
                    "personnel_units": 41030,
                    "tanks": 1768,
                    "armoured_fighting_vehicles": 4011,
                    "artillery_systems": 932,
                    "mlrs": 259,
                    "aa_warfare_systems": 117,
                    "planes": 223,
                    "helicopters": 190,
                    "vehicles_fuel_tanks": 2912,
                    "warships_cutters": 15,
                    "cruise_missiles": 174,
                    "uav_systems": 736,
                    "special_military_equip": 82,
                    "atgm_srbm_systems": 4
                }
            },
            {
                "date": "2022-08-02",
                "day": 160,
                "resource": "https://www.facebook.com/MinistryofDefence.UA/posts/pfbid0YAJs9AusF9ZL1njaj1KuCTXCrT9H5MUAnV42WquhHMECr3zuP7wqTnFWtRdgWkerl",
                "stats": {
                    "personnel_units": 41170,
                    "tanks": 1768,
                    "armoured_fighting_vehicles": 4014,
                    "artillery_systems": 936,
                    "mlrs": 259,
                    "aa_warfare_systems": 117,
                    "planes": 223,
                    "helicopters": 191,
                    "vehicles_fuel_tanks": 2914,
                    "warships_cutters": 15,
                    "cruise_missiles": 174,
                    "uav_systems": 739,
                    "special_military_equip": 82,
                    "atgm_srbm_systems": 4
                }
            },
            {
                "date": "2022-08-03",
                "day": 161,
                "resource": "https://www.facebook.com/MinistryofDefence.UA/posts/pfbid02MgzRL9a6zEm5n988JA754RcbfyoRDfkckrJDTHg9s2aDEEfwH5at5CjABLSNkyE8l",
                "stats": {
                    "personnel_units": 41350,
                    "tanks": 1774,
                    "armoured_fighting_vehicles": 4022,
                    "artillery_systems": 939,
                    "mlrs": 259,
                    "aa_warfare_systems": 118,
                    "planes": 223,
                    "helicopters": 191,
                    "vehicles_fuel_tanks": 2922,
                    "warships_cutters": 15,
                    "cruise_missiles": 180,
                    "uav_systems": 740,
                    "special_military_equip": 83,
                    "atgm_srbm_systems": 4
                }
            },
            {
                "date": "2022-08-04",
                "day": 162,
                "resource": "https://www.facebook.com/MinistryofDefence.UA/posts/pfbid0oQ39fdWMHo3u4JgQQaPpLX5Xp6mzRAmiMgYnu9AX4sh7gwQnPjP9adJtgvwfxjw4l",
                "stats": {
                    "personnel_units": 41500,
                    "tanks": 1789,
                    "armoured_fighting_vehicles": 4026,
                    "artillery_systems": 946,
                    "mlrs": 260,
                    "aa_warfare_systems": 118,
                    "planes": 223,
                    "helicopters": 191,
                    "vehicles_fuel_tanks": 2960,
                    "warships_cutters": 15,
                    "cruise_missiles": 182,
                    "uav_systems": 742,
                    "special_military_equip": 83,
                    "atgm_srbm_systems": 4
                }
            },
            {
                "date": "2022-08-05",
                "day": 163,
                "resource": "https://www.facebook.com/MinistryofDefence.UA/posts/pfbid0KADPBTPNNTUvFzSyXdQ6tNAKBaJviFcvegFhYxq2DRNHaWwLJQiyAG8ow21y3bwdl",
                "stats": {
                    "personnel_units": 41650,
                    "tanks": 1792,
                    "armoured_fighting_vehicles": 4032,
                    "artillery_systems": 950,
                    "mlrs": 260,
                    "aa_warfare_systems": 123,
                    "planes": 223,
                    "helicopters": 191,
                    "vehicles_fuel_tanks": 2964,
                    "warships_cutters": 15,
                    "cruise_missiles": 182,
                    "uav_systems": 742,
                    "special_military_equip": 83,
                    "atgm_srbm_systems": 4
                }
            },
            {
                "date": "2022-08-06",
                "day": 164,
                "resource": "https://www.facebook.com/MinistryofDefence.UA/posts/pfbid0TyD4kyRx45uVXa5rxVUPL57beMuMVK6iCeRoWSUCac9jx5yU3dHXCmh3ERm12L3ol",
                "stats": {
                    "personnel_units": 41900,
                    "tanks": 1802,
                    "armoured_fighting_vehicles": 4051,
                    "artillery_systems": 955,
                    "mlrs": 260,
                    "aa_warfare_systems": 127,
                    "planes": 223,
                    "helicopters": 191,
                    "vehicles_fuel_tanks": 2970,
                    "warships_cutters": 15,
                    "cruise_missiles": 182,
                    "uav_systems": 744,
                    "special_military_equip": 85,
                    "atgm_srbm_systems": 4
                }
            },
            {
                "date": "2022-08-07",
                "day": 165,
                "resource": "https://www.facebook.com/MinistryofDefence.UA/posts/pfbid02ntLHpDstheskBqxWGifAUdUwst1qGUQVeWLZWskQKF3xX6qTcCHqN1m9HZsACFzWl",
                "stats": {
                    "personnel_units": 42200,
                    "tanks": 1805,
                    "armoured_fighting_vehicles": 4055,
                    "artillery_systems": 958,
                    "mlrs": 260,
                    "aa_warfare_systems": 132,
                    "planes": 223,
                    "helicopters": 191,
                    "vehicles_fuel_tanks": 2978,
                    "warships_cutters": 15,
                    "cruise_missiles": 182,
                    "uav_systems": 750,
                    "special_military_equip": 86,
                    "atgm_srbm_systems": 4
                }
            },
            {
                "date": "2022-08-08",
                "day": 166,
                "resource": "https://www.facebook.com/MinistryofDefence.UA/posts/pfbid0GXDK3hCcvajwyM6r1A2yMRQbqZiA9bkwWfdJDmvGvB2mypsWTZ4VYKiDtehVDiZxl",
                "stats": {
                    "personnel_units": 42340,
                    "tanks": 1811,
                    "armoured_fighting_vehicles": 4070,
                    "artillery_systems": 960,
                    "mlrs": 261,
                    "aa_warfare_systems": 132,
                    "planes": 223,
                    "helicopters": 192,
                    "vehicles_fuel_tanks": 2993,
                    "warships_cutters": 15,
                    "cruise_missiles": 182,
                    "uav_systems": 754,
                    "special_military_equip": 86,
                    "atgm_srbm_systems": 4
                }
            },
            {
                "date": "2022-08-09",
                "day": 167,
                "resource": "https://www.facebook.com/MinistryofDefence.UA/posts/pfbid0UtBFAD33fou9qgZkH9LbuF4fPXE9BYSTmGqZJMwCs2SyLhRGTbPKc4h9VAAvukjql",
                "stats": {
                    "personnel_units": 42640,
                    "tanks": 1817,
                    "armoured_fighting_vehicles": 4076,
                    "artillery_systems": 964,
                    "mlrs": 261,
                    "aa_warfare_systems": 133,
                    "planes": 223,
                    "helicopters": 193,
                    "vehicles_fuel_tanks": 2998,
                    "warships_cutters": 15,
                    "cruise_missiles": 185,
                    "uav_systems": 757,
                    "special_military_equip": 87,
                    "atgm_srbm_systems": 4
                }
            },
            {
                "date": "2022-08-10",
                "day": 168,
                "resource": "https://www.facebook.com/MinistryofDefence.UA/posts/pfbid0Uo3b39qqiXVvnJkUo5HhU6JZWZ81dqpz7fRspsMavUizrK7i42bNfbX7EcsKzRYal",
                "stats": {
                    "personnel_units": 42800,
                    "tanks": 1832,
                    "armoured_fighting_vehicles": 4086,
                    "artillery_systems": 971,
                    "mlrs": 261,
                    "aa_warfare_systems": 133,
                    "planes": 232,
                    "helicopters": 193,
                    "vehicles_fuel_tanks": 3005,
                    "warships_cutters": 15,
                    "cruise_missiles": 185,
                    "uav_systems": 766,
                    "special_military_equip": 89,
                    "atgm_srbm_systems": 4
                }
            },
            {
                "date": "2022-08-11",
                "day": 169,
                "resource": "https://www.facebook.com/MinistryofDefence.UA/posts/pfbid0HKr5owPgradPrkccsYqJPeHtRrhaXqmUWJUTiMToE8nnEGx7eueqMw5Gtby9nvNel",
                "stats": {
                    "personnel_units": 43000,
                    "tanks": 1846,
                    "armoured_fighting_vehicles": 4100,
                    "artillery_systems": 974,
                    "mlrs": 261,
                    "aa_warfare_systems": 134,
                    "planes": 232,
                    "helicopters": 193,
                    "vehicles_fuel_tanks": 3018,
                    "warships_cutters": 15,
                    "cruise_missiles": 185,
                    "uav_systems": 772,
                    "special_military_equip": 90,
                    "atgm_srbm_systems": 4
                }
            },
            {
                "date": "2022-08-12",
                "day": 170,
                "resource": "https://www.facebook.com/MinistryofDefence.UA/posts/pfbid0bH4GLeKBcQRYX75oVQJyu5C6ctP8oHnNiDcRYUFcupee2a5CjQzuempnxJ9zBPvsl",
                "stats": {
                    "personnel_units": 43200,
                    "tanks": 1849,
                    "armoured_fighting_vehicles": 4108,
                    "artillery_systems": 975,
                    "mlrs": 261,
                    "aa_warfare_systems": 136,
                    "planes": 233,
                    "helicopters": 193,
                    "vehicles_fuel_tanks": 3021,
                    "warships_cutters": 15,
                    "cruise_missiles": 185,
                    "uav_systems": 778,
                    "special_military_equip": 90,
                    "atgm_srbm_systems": 4
                }
            },
            {
                "date": "2022-08-13",
                "day": 171,
                "resource": "https://www.facebook.com/MinistryofDefence.UA/posts/pfbid02WLP1stWptRD1gey7QJmGyAuryVN3RJ6oa3WSiTiNY8Pcu9JxmSK6qWm5X2CSNkL3l",
                "stats": {
                    "personnel_units": 43400,
                    "tanks": 1856,
                    "armoured_fighting_vehicles": 4115,
                    "artillery_systems": 978,
                    "mlrs": 261,
                    "aa_warfare_systems": 136,
                    "planes": 233,
                    "helicopters": 193,
                    "vehicles_fuel_tanks": 3036,
                    "warships_cutters": 15,
                    "cruise_missiles": 187,
                    "uav_systems": 779,
                    "special_military_equip": 91,
                    "atgm_srbm_systems": 4
                }
            },
            {
                "date": "2022-08-14",
                "day": 172,
                "resource": "https://www.facebook.com/MinistryofDefence.UA/posts/pfbid0PmM8BEnR5VevYmVK7ngAA3nahYkT95GLCtDEDWNKbvFwAHw5pyEpiikqVXf8Q8jvl",
                "stats": {
                    "personnel_units": 43550,
                    "tanks": 1864,
                    "armoured_fighting_vehicles": 4126,
                    "artillery_systems": 980,
                    "mlrs": 261,
                    "aa_warfare_systems": 136,
                    "planes": 233,
                    "helicopters": 194,
                    "vehicles_fuel_tanks": 3039,
                    "warships_cutters": 15,
                    "cruise_missiles": 187,
                    "uav_systems": 784,
                    "special_military_equip": 91,
                    "atgm_srbm_systems": 4
                }
            },
            {
                "date": "2022-08-15",
                "day": 173,
                "resource": "https://www.facebook.com/MinistryofDefence.UA/posts/pfbid03vPAEZGiqDZoxnex88uXZhM8Bj3AirrVGjanZu5o8y8ojFo9NVGNvzAzSkeeabCDl",
                "stats": {
                    "personnel_units": 43750,
                    "tanks": 1876,
                    "armoured_fighting_vehicles": 4141,
                    "artillery_systems": 985,
                    "mlrs": 261,
                    "aa_warfare_systems": 136,
                    "planes": 233,
                    "helicopters": 195,
                    "vehicles_fuel_tanks": 3044,
                    "warships_cutters": 15,
                    "cruise_missiles": 187,
                    "uav_systems": 787,
                    "special_military_equip": 92,
                    "atgm_srbm_systems": 4
                }
            },
            {
                "date": "2022-08-16",
                "day": 174,
                "resource": "https://www.facebook.com/MinistryofDefence.UA/posts/pfbid0dExyDSLiwFCEcYJVp7vyUCqD6T2qw1yzKME7TmYSMxoa9vDKmyXQKMg4YJHvhCrdl?__cft__[0]=AZW3sqhzS5YFyLYbrHDnqu4Vh0L6xPmnwq_LWC8PoO4GRyhejdzx9XGqvKM6grAdAuvULKpTqNKwvkhx6j9-Hqz3ijeA-sNtK1FPJ8QxiG4u1Q-NLNWJ6EnqpnvdrzIpoL-y7SVPu1I2kxtA7Iqk9snLL0nq5SDJSZjlqtzMus5nrGWt2SwOE8BEbOLK7iuZVO86RM9uPrDOasWwvaGGzKGt&__tn__=%2CO%2CP-R",
                "stats": {
                    "personnel_units": 43900,
                    "tanks": 1880,
                    "armoured_fighting_vehicles": 4152,
                    "artillery_systems": 989,
                    "mlrs": 263,
                    "aa_warfare_systems": 136,
                    "planes": 233,
                    "helicopters": 196,
                    "vehicles_fuel_tanks": 3049,
                    "warships_cutters": 15,
                    "cruise_missiles": 190,
                    "uav_systems": 790,
                    "special_military_equip": 92,
                    "atgm_srbm_systems": 4
                }
            },
            {
                "date": "2022-08-17",
                "day": 175,
                "resource": "https://www.facebook.com/MinistryofDefence.UA/posts/pfbid0RrgWDLrRrUB41aPehjuHs5TnTWu92qDdeD9pDShqVJFsAzHBBXvQvPowHFEjh9Lvl?__cft__[0]=AZXrpAGXiH5ApponDgGtYABw73-YD8vHD8JiNbQw66Ir36gG6lq-87Kz8x3x44Hj3YZWb8KlzWEllzswDVbbyIFJ7TZzQlJrrdr_7HjNr5lK4XcxhVe1E9pbgH8YH8zpkaDCI0K1xzYCc5D45XJdAoOD7jl_hjQTpHtY_3mOv80kMoqebB3y4kMjzrqSNaUN1AZNNxrsbby9kidJnwGYP_Kz&__tn__=%2CO%2CP-R",
                "stats": {
                    "personnel_units": 44100,
                    "tanks": 1886,
                    "armoured_fighting_vehicles": 4162,
                    "artillery_systems": 993,
                    "mlrs": 263,
                    "aa_warfare_systems": 136,
                    "planes": 233,
                    "helicopters": 196,
                    "vehicles_fuel_tanks": 3054,
                    "warships_cutters": 15,
                    "cruise_missiles": 190,
                    "uav_systems": 792,
                    "special_military_equip": 93,
                    "atgm_srbm_systems": 4
                }
            },
            {
                "date": "2022-08-18",
                "day": 176,
                "resource": "https://www.facebook.com/MinistryofDefence.UA/posts/pfbid02VsQcwEw6crU36n9u4KBSdMfSkbc29vGqqMLf5rRzTsFDiCd8ju1cZsa7VFYufR5Dl?__cft__[0]=AZWNQGtaPGFXKdcNRt6CmsOIXvaJBPHlgX1c6ZjyZo6JeTz5i_eLsckvbhMjY-6-ncCXtZX4C63Z-pqzR_4pGrH-fTiFDdXsirBLyPGQFGkbwbsdubJLj5P5GdXPiwhJBD9cHnfPgWIbVmZpBgCGRTAemZmNWv9pjrmYNfLC95PFauB33d0lYemV-H38rMRLIlKozRRNzvWgtbwjeagsvJ8q&__tn__=%2CO%2CP-R",
                "stats": {
                    "personnel_units": 44300,
                    "tanks": 1889,
                    "armoured_fighting_vehicles": 4179,
                    "artillery_systems": 1010,
                    "mlrs": 265,
                    "aa_warfare_systems": 136,
                    "planes": 234,
                    "helicopters": 197,
                    "vehicles_fuel_tanks": 3061,
                    "warships_cutters": 15,
                    "cruise_missiles": 190,
                    "uav_systems": 793,
                    "special_military_equip": 93,
                    "atgm_srbm_systems": 4
                }
            },
            {
                "date": "2022-08-19",
                "day": 177,
                "resource": "https://www.facebook.com/MinistryofDefence.UA/posts/pfbid02zDZpVe7D4cHdXAvokx3gDVkUFDcCg1Me2Vq7ekGqLSkgr2wpLNLiR7R6TwY9CqyMl?__cft__[0]=AZUfVgCZERJe3h6h1lMlJfyt6l-SQHrU4Nw4EksQQxmzAXElukQSl9rASblZtPCZsgwqct57rMbSguY3l1LNcWUEcH9LOLjXMJXM_8q6HXKarZAVTqrk-jH9d-tz0JuCyqXALTG8gtjmEFdtzKhS8w4llkYpRF82CVslUPcketvSy_qJvMEeFoWwhIKMaKPPZDZDSwMaSnG6_CvUqPElIcwv&__tn__=%2CO%2CP-R",
                "stats": {
                    "personnel_units": 44700,
                    "tanks": 1899,
                    "armoured_fighting_vehicles": 4195,
                    "artillery_systems": 1016,
                    "mlrs": 266,
                    "aa_warfare_systems": 141,
                    "planes": 234,
                    "helicopters": 197,
                    "vehicles_fuel_tanks": 3130,
                    "warships_cutters": 15,
                    "cruise_missiles": 190,
                    "uav_systems": 795,
                    "special_military_equip": 94,
                    "atgm_srbm_systems": 4
                }
            },
            {
                "date": "2022-08-20",
                "day": 178,
                "resource": "https://www.facebook.com/MinistryofDefence.UA/posts/pfbid0GHTaLghXYLSRBX4DuDufU51kog1VBTDfWjPjvxkqnki3kLFN8KFV5ybExWkWWqqyl",
                "stats": {
                    "personnel_units": 44900,
                    "tanks": 1907,
                    "armoured_fighting_vehicles": 4212,
                    "artillery_systems": 1018,
                    "mlrs": 266,
                    "aa_warfare_systems": 141,
                    "planes": 234,
                    "helicopters": 197,
                    "vehicles_fuel_tanks": 3137,
                    "warships_cutters": 15,
                    "cruise_missiles": 190,
                    "uav_systems": 803,
                    "special_military_equip": 97,
                    "atgm_srbm_systems": 4
                }
            },
            {
                "date": "2022-08-21",
                "day": 179,
                "resource": "https://www.facebook.com/MinistryofDefence.UA/posts/pfbid0HTwAEZ4BWfPVob8BSY767Dmi4Lmsgr5PtAbvoZ4jeR2jG7y6YkNqkEwmHRaV3xCnl",
                "stats": {
                    "personnel_units": 45200,
                    "tanks": 1912,
                    "armoured_fighting_vehicles": 4224,
                    "artillery_systems": 1028,
                    "mlrs": 266,
                    "aa_warfare_systems": 141,
                    "planes": 234,
                    "helicopters": 197,
                    "vehicles_fuel_tanks": 3143,
                    "warships_cutters": 15,
                    "cruise_missiles": 190,
                    "uav_systems": 806,
                    "special_military_equip": 99,
                    "atgm_srbm_systems": 4
                }
            },
            {
                "date": "2022-08-22",
                "day": 180,
                "resource": "https://www.facebook.com/MinistryofDefence.UA/posts/pfbid0axzUh1rQtXodMsHgVvKvKwQ5fKAVrffzu9suMTd9M87KYCtPtgKrNBvu3tXWbPwl",
                "stats": {
                    "personnel_units": 45400,
                    "tanks": 1919,
                    "armoured_fighting_vehicles": 4230,
                    "artillery_systems": 1032,
                    "mlrs": 266,
                    "aa_warfare_systems": 145,
                    "planes": 234,
                    "helicopters": 198,
                    "vehicles_fuel_tanks": 3149,
                    "warships_cutters": 15,
                    "cruise_missiles": 194,
                    "uav_systems": 815,
                    "special_military_equip": 99,
                    "atgm_srbm_systems": 4
                }
            },
            {
                "date": "2022-08-23",
                "day": 181,
                "resource": "https://www.facebook.com/MinistryofDefence.UA/posts/pfbid02TrZDPMhiLqfubfazZj4dfrKnJzeVPBfpwz6rsUV7okXxt65aZtk3kY3Jj2X9HdpEl",
                "stats": {
                    "personnel_units": 45550,
                    "tanks": 1921,
                    "armoured_fighting_vehicles": 4238,
                    "artillery_systems": 1033,
                    "mlrs": 266,
                    "aa_warfare_systems": 146,
                    "planes": 234,
                    "helicopters": 198,
                    "vehicles_fuel_tanks": 3150,
                    "warships_cutters": 15,
                    "cruise_missiles": 196,
                    "uav_systems": 817,
                    "special_military_equip": 99,
                    "atgm_srbm_systems": 4
                }
            },
            {
                "date": "2022-08-24",
                "day": 182,
                "resource": "https://www.facebook.com/MinistryofDefence.UA/posts/pfbid0p2dkDxqEKureuMCEjyzjdvjTjSzBXeJPYJj29MWpe1ESjEen91WRCLdESfTnuVatl",
                "stats": {
                    "personnel_units": 45700,
                    "tanks": 1924,
                    "armoured_fighting_vehicles": 4243,
                    "artillery_systems": 1036,
                    "mlrs": 266,
                    "aa_warfare_systems": 147,
                    "planes": 234,
                    "helicopters": 199,
                    "vehicles_fuel_tanks": 3160,
                    "warships_cutters": 15,
                    "cruise_missiles": 196,
                    "uav_systems": 819,
                    "special_military_equip": 99,
                    "atgm_srbm_systems": 4
                }
            },
            {
                "date": "2022-08-25",
                "day": 183,
                "resource": "https://www.facebook.com/MinistryofDefence.UA/posts/pfbid02Y2tphYjp5JCh3whncTdt5XSFXyruqHf35p44omPWYNk391JwKJmYQBaC1w3vK7Kcl",
                "stats": {
                    "personnel_units": 45850,
                    "tanks": 1929,
                    "armoured_fighting_vehicles": 4245,
                    "artillery_systems": 1037,
                    "mlrs": 272,
                    "aa_warfare_systems": 148,
                    "planes": 234,
                    "helicopters": 202,
                    "vehicles_fuel_tanks": 3160,
                    "warships_cutters": 15,
                    "cruise_missiles": 196,
                    "uav_systems": 828,
                    "special_military_equip": 99,
                    "atgm_srbm_systems": 4
                }
            },
            {
                "date": "2022-08-26",
                "day": 184,
                "resource": "https://www.facebook.com/MinistryofDefence.UA/posts/pfbid0U8iqFWrvXnBfyvbBnJi3q2bhy4UhNSzFeqUgWSyChUzjDCYt3zkQFGv57gRJKUQLl",
                "stats": {
                    "personnel_units": 46250,
                    "tanks": 1936,
                    "armoured_fighting_vehicles": 4251,
                    "artillery_systems": 1040,
                    "mlrs": 272,
                    "aa_warfare_systems": 148,
                    "planes": 234,
                    "helicopters": 202,
                    "vehicles_fuel_tanks": 3162,
                    "warships_cutters": 15,
                    "cruise_missiles": 196,
                    "uav_systems": 834,
                    "special_military_equip": 99,
                    "atgm_srbm_systems": 4
                }
            },
            {
                "date": "2022-08-27",
                "day": 185,
                "resource": "https://www.facebook.com/MinistryofDefence.UA/posts/pfbid02ykvYt6r4yXUb3gcSKYm4MhZwRJifNBUvowyHhQ1VZzSY9h26keFrstXLs6gnZGHhl",
                "stats": {
                    "personnel_units": 46500,
                    "tanks": 1939,
                    "armoured_fighting_vehicles": 4254,
                    "artillery_systems": 1045,
                    "mlrs": 274,
                    "aa_warfare_systems": 148,
                    "planes": 234,
                    "helicopters": 202,
                    "vehicles_fuel_tanks": 3165,
                    "warships_cutters": 15,
                    "cruise_missiles": 196,
                    "uav_systems": 836,
                    "special_military_equip": 99,
                    "atgm_srbm_systems": 4
                }
            },
            {
                "date": "2022-08-28",
                "day": 186,
                "resource": "https://www.facebook.com/MinistryofDefence.UA/posts/pfbid0356yL6iBLTRgGqFCvoyP6DkqsdbFzdzQtC4NeLqdUzayrowSCDYJYCxgeBUFB4kJ2l",
                "stats": {
                    "personnel_units": 46750,
                    "tanks": 1942,
                    "armoured_fighting_vehicles": 4257,
                    "artillery_systems": 1050,
                    "mlrs": 274,
                    "aa_warfare_systems": 148,
                    "planes": 234,
                    "helicopters": 202,
                    "vehicles_fuel_tanks": 3171,
                    "warships_cutters": 15,
                    "cruise_missiles": 196,
                    "uav_systems": 838,
                    "special_military_equip": 99,
                    "atgm_srbm_systems": 4
                }
            },
            {
                "date": "2022-08-29",
                "day": 187,
                "resource": "https://www.facebook.com/MinistryofDefence.UA/posts/pfbid0G4U71iRKLqqJvF1jRYBQ3bofhVCz8Uq3oz8wCMg1ULeMioU4PmAjcaMsGyGQbL4fl",
                "stats": {
                    "personnel_units": 47100,
                    "tanks": 1947,
                    "armoured_fighting_vehicles": 4269,
                    "artillery_systems": 1060,
                    "mlrs": 279,
                    "aa_warfare_systems": 149,
                    "planes": 234,
                    "helicopters": 203,
                    "vehicles_fuel_tanks": 3188,
                    "warships_cutters": 15,
                    "cruise_missiles": 196,
                    "uav_systems": 844,
                    "special_military_equip": 101,
                    "atgm_srbm_systems": 4
                }
            },
            {
                "date": "2022-08-30",
                "day": 188,
                "resource": "https://www.facebook.com/MinistryofDefence.UA/posts/pfbid02umQ9e9jAMVmiUk7tVZvbNpdxGZbvUnpEEyqyRR1rag1VssqNjbUk57UmnjUkBCZfl",
                "stats": {
                    "personnel_units": 47550,
                    "tanks": 1954,
                    "armoured_fighting_vehicles": 4294,
                    "artillery_systems": 1079,
                    "mlrs": 282,
                    "aa_warfare_systems": 151,
                    "planes": 234,
                    "helicopters": 204,
                    "vehicles_fuel_tanks": 3217,
                    "warships_cutters": 15,
                    "cruise_missiles": 196,
                    "uav_systems": 847,
                    "special_military_equip": 103,
                    "atgm_srbm_systems": 4
                }
            },
            {
                "date": "2022-08-31",
                "day": 189,
                "resource": "https://www.facebook.com/MinistryofDefence.UA/posts/pfbid02FHUS8hVJwhrZVKP3afNhPg9gjKqKSzkwvyDV7qAJTuY1v9EzoLp8ZFJB3BGxN6qil",
                "stats": {
                    "personnel_units": 47900,
                    "tanks": 1974,
                    "armoured_fighting_vehicles": 4312,
                    "artillery_systems": 1091,
                    "mlrs": 285,
                    "aa_warfare_systems": 152,
                    "planes": 234,
                    "helicopters": 204,
                    "vehicles_fuel_tanks": 3236,
                    "warships_cutters": 15,
                    "cruise_missiles": 196,
                    "uav_systems": 849,
                    "special_military_equip": 103,
                    "atgm_srbm_systems": 4
                }
            },
            {
                "date": "2022-09-01",
                "day": 190,
                "resource": "https://www.facebook.com/MinistryofDefence.UA/posts/pfbid0GQ22Gw5Nsw8F5iARhwX8K7DUrzpWqdqdsAXLvf1pLaAUtLfUgxB3AACXLp9FvN8Al",
                "stats": {
                    "personnel_units": 48350,
                    "tanks": 1997,
                    "armoured_fighting_vehicles": 4345,
                    "artillery_systems": 1115,
                    "mlrs": 287,
                    "aa_warfare_systems": 153,
                    "planes": 234,
                    "helicopters": 205,
                    "vehicles_fuel_tanks": 3239,
                    "warships_cutters": 15,
                    "cruise_missiles": 196,
                    "uav_systems": 851,
                    "special_military_equip": 104,
                    "atgm_srbm_systems": 4
                }
            },
            {
                "date": "2022-09-02",
                "day": 191,
                "resource": "https://www.facebook.com/MinistryofDefence.UA/posts/pfbid0CtfnvoQ86Vi5aCPjzu6cDwb12wTXqR6xx5PUkhKp391MmDBMmHweRUsmVG3144nNl",
                "stats": {
                    "personnel_units": 48700,
                    "tanks": 2009,
                    "armoured_fighting_vehicles": 4366,
                    "artillery_systems": 1126,
                    "mlrs": 289,
                    "aa_warfare_systems": 153,
                    "planes": 234,
                    "helicopters": 205,
                    "vehicles_fuel_tanks": 3247,
                    "warships_cutters": 15,
                    "cruise_missiles": 198,
                    "uav_systems": 853,
                    "special_military_equip": 105,
                    "atgm_srbm_systems": 4
                }
            },
            {
                "date": "2022-09-03",
                "day": 192,
                "resource": "https://www.facebook.com/MinistryofDefence.UA/posts/pfbid02E1DHZppy1YFjJRTFRuC63eFt2g3BZR3hcP6kHfQTuN4cFH4QpmmnHCA3xVGj4oBGl",
                "stats": {
                    "personnel_units": 49050,
                    "tanks": 2034,
                    "armoured_fighting_vehicles": 4403,
                    "artillery_systems": 1134,
                    "mlrs": 293,
                    "aa_warfare_systems": 153,
                    "planes": 235,
                    "helicopters": 205,
                    "vehicles_fuel_tanks": 3268,
                    "warships_cutters": 15,
                    "cruise_missiles": 203,
                    "uav_systems": 864,
                    "special_military_equip": 105,
                    "atgm_srbm_systems": 4
                }
            },
            {
                "date": "2022-09-04",
                "day": 193,
                "resource": "https://www.facebook.com/MinistryofDefence.UA/posts/pfbid0A82H8P6wyum29HeoJ77dnDv57s6rMibMxVBk3EZscfzRhK5FVBSs7zQsd2RCbPmml",
                "stats": {
                    "personnel_units": 49500,
                    "tanks": 2049,
                    "armoured_fighting_vehicles": 4430,
                    "artillery_systems": 1147,
                    "mlrs": 294,
                    "aa_warfare_systems": 156,
                    "planes": 236,
                    "helicopters": 206,
                    "vehicles_fuel_tanks": 3276,
                    "warships_cutters": 15,
                    "cruise_missiles": 203,
                    "uav_systems": 864,
                    "special_military_equip": 106,
                    "atgm_srbm_systems": 4
                }
            },
            {
                "date": "2022-09-05",
                "day": 194,
                "resource": "https://www.facebook.com/MinistryofDefence.UA/posts/pfbid058cjZnLPUuRvcgMHCdrfxR8SBXN6tzxNxw1CwrrBJxYvBBRFr8pUpDUvfuGjEjqol",
                "stats": {
                    "personnel_units": 49800,
                    "tanks": 2068,
                    "armoured_fighting_vehicles": 4459,
                    "artillery_systems": 1157,
                    "mlrs": 294,
                    "aa_warfare_systems": 156,
                    "planes": 236,
                    "helicopters": 206,
                    "vehicles_fuel_tanks": 3286,
                    "warships_cutters": 15,
                    "cruise_missiles": 205,
                    "uav_systems": 867,
                    "special_military_equip": 107,
                    "atgm_srbm_systems": 4
                }
            },
            {
                "date": "2022-09-06",
                "day": 195,
                "resource": "https://www.facebook.com/MinistryofDefence.UA/posts/pfbid035iuaGDAPy1AuZxTcQ9DFgie8aN5SAvyrvae9mo2emXYs3fXQe2JHys7kfkdMQ1p8l",
                "stats": {
                    "personnel_units": 50150,
                    "tanks": 2077,
                    "armoured_fighting_vehicles": 4484,
                    "artillery_systems": 1179,
                    "mlrs": 296,
                    "aa_warfare_systems": 156,
                    "planes": 236,
                    "helicopters": 207,
                    "vehicles_fuel_tanks": 3305,
                    "warships_cutters": 15,
                    "cruise_missiles": 209,
                    "uav_systems": 876,
                    "special_military_equip": 109,
                    "atgm_srbm_systems": 4
                }
            },
            {
                "date": "2022-09-07",
                "day": 196,
                "resource": "https://www.facebook.com/MinistryofDefence.UA/posts/pfbid0FCZgHvBX9oT19iq5kU1zCkU11rq2xQTZmnyK5XUgc7KJvTBrt44r14fvvwPZKiD7l",
                "stats": {
                    "personnel_units": 50610,
                    "tanks": 2097,
                    "armoured_fighting_vehicles": 4520,
                    "artillery_systems": 1194,
                    "mlrs": 300,
                    "aa_warfare_systems": 156,
                    "planes": 237,
                    "helicopters": 208,
                    "vehicles_fuel_tanks": 3320,
                    "warships_cutters": 15,
                    "cruise_missiles": 214,
                    "uav_systems": 880,
                    "special_military_equip": 109,
                    "atgm_srbm_systems": 4
                }
            },
            {
                "date": "2022-09-08",
                "day": 197,
                "resource": "https://www.facebook.com/MinistryofDefence.UA/posts/pfbid033NwZYMoBpo82w61EcHGwjhRRBvRKbvNeAuM2j2352Gf7jWvLfs1wcBspZEvQunWdl",
                "stats": {
                    "personnel_units": 51250,
                    "tanks": 2112,
                    "armoured_fighting_vehicles": 4557,
                    "artillery_systems": 1226,
                    "mlrs": 305,
                    "aa_warfare_systems": 159,
                    "planes": 239,
                    "helicopters": 210,
                    "vehicles_fuel_tanks": 3344,
                    "warships_cutters": 15,
                    "cruise_missiles": 214,
                    "uav_systems": 884,
                    "special_military_equip": 110,
                    "atgm_srbm_systems": 4
                }
            },
            {
                "date": "2022-09-09",
                "day": 198,
                "resource": "https://www.facebook.com/MinistryofDefence.UA/posts/pfbid02LziHxydrvSLAAWGqCgn5JoorqPVy5LuKpAsoXrC39c2rtNMKbisLZhbr5LXxQtKUl",
                "stats": {
                    "personnel_units": 51900,
                    "tanks": 2122,
                    "armoured_fighting_vehicles": 4575,
                    "artillery_systems": 1237,
                    "mlrs": 306,
                    "aa_warfare_systems": 159,
                    "planes": 239,
                    "helicopters": 211,
                    "vehicles_fuel_tanks": 3399,
                    "warships_cutters": 15,
                    "cruise_missiles": 214,
                    "uav_systems": 888,
                    "special_military_equip": 114,
                    "atgm_srbm_systems": 4
                }
            },
            {
                "date": "2022-09-10",
                "day": 199,
                "resource": "https://www.facebook.com/MinistryofDefence.UA/posts/pfbid0JMVZfZZXNSeqp4MCMah7TGZ4LGb4TUPEvS2VncPpEDTmWEdAwUpiShaGKxbkJAqWl",
                "stats": {
                    "personnel_units": 52250,
                    "tanks": 2136,
                    "armoured_fighting_vehicles": 4584,
                    "artillery_systems": 1259,
                    "mlrs": 311,
                    "aa_warfare_systems": 162,
                    "planes": 239,
                    "helicopters": 212,
                    "vehicles_fuel_tanks": 3426,
                    "warships_cutters": 15,
                    "cruise_missiles": 215,
                    "uav_systems": 898,
                    "special_military_equip": 116,
                    "atgm_srbm_systems": 4
                }
            },
            {
                "date": "2022-09-11",
                "day": 200,
                "resource": "https://www.facebook.com/MinistryofDefence.UA/posts/pfbid02fhHAuNpz5c9SHeiMgb33qW8iW5ZS5fUmy6xjwT7GoQ7Ru4bbQrXa91nnYpxNQ3WMl",
                "stats": {
                    "personnel_units": 52650,
                    "tanks": 2154,
                    "armoured_fighting_vehicles": 4617,
                    "artillery_systems": 1263,
                    "mlrs": 311,
                    "aa_warfare_systems": 162,
                    "planes": 242,
                    "helicopters": 213,
                    "vehicles_fuel_tanks": 3445,
                    "warships_cutters": 15,
                    "cruise_missiles": 216,
                    "uav_systems": 902,
                    "special_military_equip": 117,
                    "atgm_srbm_systems": 4
                }
            },
            {
                "date": "2022-09-12",
                "day": 201,
                "resource": "https://www.facebook.com/MinistryofDefence.UA/posts/pfbid031YTsvAmXhcwgfVBeBENHvh6LxYZMk3XbHqGRc3twiawVnPdutQNhm8dt5fhTwkH5l",
                "stats": {
                    "personnel_units": 52950,
                    "tanks": 2168,
                    "armoured_fighting_vehicles": 4640,
                    "artillery_systems": 1269,
                    "mlrs": 311,
                    "aa_warfare_systems": 162,
                    "planes": 243,
                    "helicopters": 213,
                    "vehicles_fuel_tanks": 3463,
                    "warships_cutters": 15,
                    "cruise_missiles": 216,
                    "uav_systems": 903,
                    "special_military_equip": 117,
                    "atgm_srbm_systems": 4
                }
            },
            {
                "date": "2022-09-13",
                "day": 202,
                "resource": "https://www.facebook.com/MinistryofDefence.UA/posts/pfbid0vqSVoxUE3uLmsfVVnKTJ5P2s4aXK3y3HAF8S5VW7dvfwKUewqgeDKC9PMSj8hskyl",
                "stats": {
                    "personnel_units": 53300,
                    "tanks": 2175,
                    "armoured_fighting_vehicles": 4662,
                    "artillery_systems": 1279,
                    "mlrs": 311,
                    "aa_warfare_systems": 165,
                    "planes": 244,
                    "helicopters": 213,
                    "vehicles_fuel_tanks": 3469,
                    "warships_cutters": 15,
                    "cruise_missiles": 233,
                    "uav_systems": 904,
                    "special_military_equip": 117,
                    "atgm_srbm_systems": 4
                }
            }
        ],
        "paging": {
            "next_url": "https://russianwarship.rip/api/v1/statistics?offset=200&limit=50",
            "prev_url": "https://russianwarship.rip/api/v1/statistics?offset=100&limit=50",
            "first_url": "https://russianwarship.rip/api/v1/statistics?offset=0&limit=50",
            "last_url": "https://russianwarship.rip/api/v1/statistics?offset=250&limit=46"
        }
    }
}